<?xml version="1.0" encoding="utf-8"?>
<document>
 <Head/>
 <Municipio>
  <Nome>Agua_Branca</Nome>
  <ID>270010</ID>
  <UF>AL</UF>
  <Indicador>
   <Nome>Moradpartperurb</Nome>
   <Dado>
    <Ano>1991</Ano>
    <Valor>5.522</Valor>
   </Dado>
   <Dado>
    <Ano>2000</Ano>
    <Valor>4.484</Valor>
   </Dado>
   <Dado>
    <Ano>2010</Ano>
    <Valor>5.090</Valor>
   </Dado>
  </Indicador>
 </Municipio>
 <Municipio>
  <Nome>Anadia</Nome>
  <ID>270020</ID>
  <UF>AL</UF>
  <Indicador>
   <Nome>Moradpartperurb</Nome>
   <Dado>
    <Ano>1991</Ano>
    <Valor>7.861</Valor>
   </Dado>
   <Dado>
    <Ano>2000</Ano>
    <Valor>9.101</Valor>
   </Dado>
   <Dado>
    <Ano>2010</Ano>
    <Valor>8.943</Valor>
   </Dado>
  </Indicador>
 </Municipio>
 <Municipio>
  <Nome>Arapiraca</Nome>
  <ID>270030</ID>
  <UF>AL</UF>
  <Indicador>
   <Nome>Moradpartperurb</Nome>
   <Dado>
    <Ano>1991</Ano>
    <Valor>130.210</Valor>
   </Dado>
   <Dado>
    <Ano>2000</Ano>
    <Valor>151.574</Valor>
   </Dado>
   <Dado>
    <Ano>2010</Ano>
    <Valor>180.974</Valor>
   </Dado>
  </Indicador>
 </Municipio>
 <Municipio>
  <Nome>Atalaia</Nome>
  <ID>270040</ID>
  <UF>AL</UF>
  <Indicador>
   <Nome>Moradpartperurb</Nome>
   <Dado>
    <Ano>1991</Ano>
    <Valor>14.186</Valor>
   </Dado>
   <Dado>
    <Ano>2000</Ano>
    <Valor>17.701</Valor>
   </Dado>
   <Dado>
    <Ano>2010</Ano>
    <Valor>22.095</Valor>
   </Dado>
  </Indicador>
 </Municipio>
 <Municipio>
  <Nome>Barra_de_Santo_Antonio</Nome>
  <ID>270050</ID>
  <UF>AL</UF>
  <Indicador>
   <Nome>Moradpartperurb</Nome>
   <Dado>
    <Ano>1991</Ano>
    <Valor>5.628</Valor>
   </Dado>
   <Dado>
    <Ano>2000</Ano>
    <Valor>8.983</Valor>
   </Dado>
   <Dado>
    <Ano>2010</Ano>
    <Valor>13.121</Valor>
   </Dado>
  </Indicador>
 </Municipio>
 <Municipio>
  <Nome>Barra_de_Sao_Miguel</Nome>
  <ID>270060</ID>
  <UF>AL</UF>
  <Indicador>
   <Nome>Moradpartperurb</Nome>
   <Dado>
    <Ano>1991</Ano>
    <Valor>3.439</Valor>
   </Dado>
   <Dado>
    <Ano>2000</Ano>
    <Valor>5.184</Valor>
   </Dado>
   <Dado>
    <Ano>2010</Ano>
    <Valor>6.394</Valor>
   </Dado>
  </Indicador>
 </Municipio>
 <Municipio>
  <Nome>Batalha</Nome>
  <ID>270070</ID>
  <UF>AL</UF>
  <Indicador>
   <Nome>Moradpartperurb</Nome>
   <Dado>
    <Ano>1991</Ano>
    <Valor>8.242</Valor>
   </Dado>
   <Dado>
    <Ano>2000</Ano>
    <Valor>10.104</Valor>
   </Dado>
   <Dado>
    <Ano>2010</Ano>
    <Valor>11.768</Valor>
   </Dado>
  </Indicador>
 </Municipio>
 <Municipio>
  <Nome>Belem</Nome>
  <ID>270080</ID>
  <UF>AL</UF>
  <Indicador>
   <Nome>Moradpartperurb</Nome>
   <Dado>
    <Ano>1991</Ano>
    <Valor>1.817</Valor>
   </Dado>
   <Dado>
    <Ano>2000</Ano>
    <Valor>1.823</Valor>
   </Dado>
   <Dado>
    <Ano>2010</Ano>
    <Valor>1.869</Valor>
   </Dado>
  </Indicador>
 </Municipio>
 <Municipio>
  <Nome>Belo_Monte</Nome>
  <ID>270090</ID>
  <UF>AL</UF>
  <Indicador>
   <Nome>Moradpartperurb</Nome>
   <Dado>
    <Ano>1991</Ano>
    <Valor>1.045</Valor>
   </Dado>
   <Dado>
    <Ano>2000</Ano>
    <Valor>1.226</Valor>
   </Dado>
   <Dado>
    <Ano>2010</Ano>
    <Valor>1.166</Valor>
   </Dado>
  </Indicador>
 </Municipio>
 <Municipio>
  <Nome>Boca_da_Mata</Nome>
  <ID>270100</ID>
  <UF>AL</UF>
  <Indicador>
   <Nome>Moradpartperurb</Nome>
   <Dado>
    <Ano>1991</Ano>
    <Valor>11.464</Valor>
   </Dado>
   <Dado>
    <Ano>2000</Ano>
    <Valor>15.367</Valor>
   </Dado>
   <Dado>
    <Ano>2010</Ano>
    <Valor>17.434</Valor>
   </Dado>
  </Indicador>
 </Municipio>
 <Municipio>
  <Nome>Branquinha</Nome>
  <ID>270110</ID>
  <UF>AL</UF>
  <Indicador>
   <Nome>Moradpartperurb</Nome>
   <Dado>
    <Ano>1991</Ano>
    <Valor>2.688</Valor>
   </Dado>
   <Dado>
    <Ano>2000</Ano>
    <Valor>5.552</Valor>
   </Dado>
   <Dado>
    <Ano>2010</Ano>
    <Valor>6.115</Valor>
   </Dado>
  </Indicador>
 </Municipio>
 <Municipio>
  <Nome>Cacimbinhas</Nome>
  <ID>270120</ID>
  <UF>AL</UF>
  <Indicador>
   <Nome>Moradpartperurb</Nome>
   <Dado>
    <Ano>1991</Ano>
    <Valor>4.056</Valor>
   </Dado>
   <Dado>
    <Ano>2000</Ano>
    <Valor>4.209</Valor>
   </Dado>
   <Dado>
    <Ano>2010</Ano>
    <Valor>5.402</Valor>
   </Dado>
  </Indicador>
 </Municipio>
 <Municipio>
  <Nome>Cajueiro</Nome>
  <ID>270130</ID>
  <UF>AL</UF>
  <Indicador>
   <Nome>Moradpartperurb</Nome>
   <Dado>
    <Ano>1991</Ano>
    <Valor>12.378</Valor>
   </Dado>
   <Dado>
    <Ano>2000</Ano>
    <Valor>13.951</Valor>
   </Dado>
   <Dado>
    <Ano>2010</Ano>
    <Valor>16.239</Valor>
   </Dado>
  </Indicador>
 </Municipio>
 <Municipio>
  <Nome>Campestre</Nome>
  <ID>270135</ID>
  <UF>AL</UF>
  <Indicador>
   <Nome>Moradpartperurb</Nome>
   <Dado>
    <Ano>1991</Ano>
    <Valor>0</Valor>
   </Dado>
   <Dado>
    <Ano>2000</Ano>
    <Valor>4.676</Valor>
   </Dado>
   <Dado>
    <Ano>2010</Ano>
    <Valor>5.433</Valor>
   </Dado>
  </Indicador>
 </Municipio>
 <Municipio>
  <Nome>Campo_Alegre</Nome>
  <ID>270140</ID>
  <UF>AL</UF>
  <Indicador>
   <Nome>Moradpartperurb</Nome>
   <Dado>
    <Ano>1991</Ano>
    <Valor>11.516</Valor>
   </Dado>
   <Dado>
    <Ano>2000</Ano>
    <Valor>16.073</Valor>
   </Dado>
   <Dado>
    <Ano>2010</Ano>
    <Valor>22.019</Valor>
   </Dado>
  </Indicador>
 </Municipio>
 <Municipio>
  <Nome>Campo_Grande</Nome>
  <ID>270150</ID>
  <UF>AL</UF>
  <Indicador>
   <Nome>Moradpartperurb</Nome>
   <Dado>
    <Ano>1991</Ano>
    <Valor>3.988</Valor>
   </Dado>
   <Dado>
    <Ano>2000</Ano>
    <Valor>3.671</Valor>
   </Dado>
   <Dado>
    <Ano>2010</Ano>
    <Valor>4.181</Valor>
   </Dado>
  </Indicador>
 </Municipio>
 <Municipio>
  <Nome>Canapi</Nome>
  <ID>270160</ID>
  <UF>AL</UF>
  <Indicador>
   <Nome>Moradpartperurb</Nome>
   <Dado>
    <Ano>1991</Ano>
    <Valor>3.314</Valor>
   </Dado>
   <Dado>
    <Ano>2000</Ano>
    <Valor>4.112</Valor>
   </Dado>
   <Dado>
    <Ano>2010</Ano>
    <Valor>5.525</Valor>
   </Dado>
  </Indicador>
 </Municipio>
 <Municipio>
  <Nome>Capela</Nome>
  <ID>270170</ID>
  <UF>AL</UF>
  <Indicador>
   <Nome>Moradpartperurb</Nome>
   <Dado>
    <Ano>1991</Ano>
    <Valor>9.684</Valor>
   </Dado>
   <Dado>
    <Ano>2000</Ano>
    <Valor>12.522</Valor>
   </Dado>
   <Dado>
    <Ano>2010</Ano>
    <Valor>12.327</Valor>
   </Dado>
  </Indicador>
 </Municipio>
 <Municipio>
  <Nome>Carneiros</Nome>
  <ID>270180</ID>
  <UF>AL</UF>
  <Indicador>
   <Nome>Moradpartperurb</Nome>
   <Dado>
    <Ano>1991</Ano>
    <Valor>2.036</Valor>
   </Dado>
   <Dado>
    <Ano>2000</Ano>
    <Valor>3.385</Valor>
   </Dado>
   <Dado>
    <Ano>2010</Ano>
    <Valor>4.580</Valor>
   </Dado>
  </Indicador>
 </Municipio>
 <Municipio>
  <Nome>Cha_Preta</Nome>
  <ID>270190</ID>
  <UF>AL</UF>
  <Indicador>
   <Nome>Moradpartperurb</Nome>
   <Dado>
    <Ano>1991</Ano>
    <Valor>3.011</Valor>
   </Dado>
   <Dado>
    <Ano>2000</Ano>
    <Valor>3.672</Valor>
   </Dado>
   <Dado>
    <Ano>2010</Ano>
    <Valor>4.452</Valor>
   </Dado>
  </Indicador>
 </Municipio>
 <Municipio>
  <Nome>Coite_do_Noia</Nome>
  <ID>270200</ID>
  <UF>AL</UF>
  <Indicador>
   <Nome>Moradpartperurb</Nome>
   <Dado>
    <Ano>1991</Ano>
    <Valor>2.081</Valor>
   </Dado>
   <Dado>
    <Ano>2000</Ano>
    <Valor>2.519</Valor>
   </Dado>
   <Dado>
    <Ano>2010</Ano>
    <Valor>3.732</Valor>
   </Dado>
  </Indicador>
 </Municipio>
 <Municipio>
  <Nome>Colonia_Leopoldina</Nome>
  <ID>270210</ID>
  <UF>AL</UF>
  <Indicador>
   <Nome>Moradpartperurb</Nome>
   <Dado>
    <Ano>1991</Ano>
    <Valor>9.524</Valor>
   </Dado>
   <Dado>
    <Ano>2000</Ano>
    <Valor>11.377</Valor>
   </Dado>
   <Dado>
    <Ano>2010</Ano>
    <Valor>15.306</Valor>
   </Dado>
  </Indicador>
 </Municipio>
 <Municipio>
  <Nome>Coqueiro_Seco</Nome>
  <ID>270220</ID>
  <UF>AL</UF>
  <Indicador>
   <Nome>Moradpartperurb</Nome>
   <Dado>
    <Ano>1991</Ano>
    <Valor>4.192</Valor>
   </Dado>
   <Dado>
    <Ano>2000</Ano>
    <Valor>4.553</Valor>
   </Dado>
   <Dado>
    <Ano>2010</Ano>
    <Valor>4.965</Valor>
   </Dado>
  </Indicador>
 </Municipio>
 <Municipio>
  <Nome>Coruripe</Nome>
  <ID>270230</ID>
  <UF>AL</UF>
  <Indicador>
   <Nome>Moradpartperurb</Nome>
   <Dado>
    <Ano>1991</Ano>
    <Valor>13.943</Valor>
   </Dado>
   <Dado>
    <Ano>2000</Ano>
    <Valor>22.199</Valor>
   </Dado>
   <Dado>
    <Ano>2010</Ano>
    <Valor>45.744</Valor>
   </Dado>
  </Indicador>
 </Municipio>
 <Municipio>
  <Nome>Craibas</Nome>
  <ID>270235</ID>
  <UF>AL</UF>
  <Indicador>
   <Nome>Moradpartperurb</Nome>
   <Dado>
    <Ano>1991</Ano>
    <Valor>5.027</Valor>
   </Dado>
   <Dado>
    <Ano>2000</Ano>
    <Valor>6.608</Valor>
   </Dado>
   <Dado>
    <Ano>2010</Ano>
    <Valor>7.305</Valor>
   </Dado>
  </Indicador>
 </Municipio>
 <Municipio>
  <Nome>Delmiro_Gouveia</Nome>
  <ID>270240</ID>
  <UF>AL</UF>
  <Indicador>
   <Nome>Moradpartperurb</Nome>
   <Dado>
    <Ano>1991</Ano>
    <Valor>31.899</Valor>
   </Dado>
   <Dado>
    <Ano>2000</Ano>
    <Valor>33.529</Valor>
   </Dado>
   <Dado>
    <Ano>2010</Ano>
    <Valor>34.807</Valor>
   </Dado>
  </Indicador>
 </Municipio>
 <Municipio>
  <Nome>Dois_Riachos</Nome>
  <ID>270250</ID>
  <UF>AL</UF>
  <Indicador>
   <Nome>Moradpartperurb</Nome>
   <Dado>
    <Ano>1991</Ano>
    <Valor>3.367</Valor>
   </Dado>
   <Dado>
    <Ano>2000</Ano>
    <Valor>4.337</Valor>
   </Dado>
   <Dado>
    <Ano>2010</Ano>
    <Valor>5.081</Valor>
   </Dado>
  </Indicador>
 </Municipio>
 <Municipio>
  <Nome>Estrela_de_Alagoas</Nome>
  <ID>270255</ID>
  <UF>AL</UF>
  <Indicador>
   <Nome>Moradpartperurb</Nome>
   <Dado>
    <Ano>1991</Ano>
    <Valor>0</Valor>
   </Dado>
   <Dado>
    <Ano>2000</Ano>
    <Valor>3.260</Valor>
   </Dado>
   <Dado>
    <Ano>2010</Ano>
    <Valor>4.023</Valor>
   </Dado>
  </Indicador>
 </Municipio>
 <Municipio>
  <Nome>Feira_Grande</Nome>
  <ID>270260</ID>
  <UF>AL</UF>
  <Indicador>
   <Nome>Moradpartperurb</Nome>
   <Dado>
    <Ano>1991</Ano>
    <Valor>2.806</Valor>
   </Dado>
   <Dado>
    <Ano>2000</Ano>
    <Valor>3.518</Valor>
   </Dado>
   <Dado>
    <Ano>2010</Ano>
    <Valor>3.418</Valor>
   </Dado>
  </Indicador>
 </Municipio>
 <Municipio>
  <Nome>Feliz_Deserto</Nome>
  <ID>270270</ID>
  <UF>AL</UF>
  <Indicador>
   <Nome>Moradpartperurb</Nome>
   <Dado>
    <Ano>1991</Ano>
    <Valor>2.641</Valor>
   </Dado>
   <Dado>
    <Ano>2000</Ano>
    <Valor>2.789</Valor>
   </Dado>
   <Dado>
    <Ano>2010</Ano>
    <Valor>3.472</Valor>
   </Dado>
  </Indicador>
 </Municipio>
 <Municipio>
  <Nome>Flexeiras</Nome>
  <ID>270280</ID>
  <UF>AL</UF>
  <Indicador>
   <Nome>Moradpartperurb</Nome>
   <Dado>
    <Ano>1991</Ano>
    <Valor>4.521</Valor>
   </Dado>
   <Dado>
    <Ano>2000</Ano>
    <Valor>6.630</Valor>
   </Dado>
   <Dado>
    <Ano>2010</Ano>
    <Valor>7.999</Valor>
   </Dado>
  </Indicador>
 </Municipio>
 <Municipio>
  <Nome>Girau_do_Ponciano</Nome>
  <ID>270290</ID>
  <UF>AL</UF>
  <Indicador>
   <Nome>Moradpartperurb</Nome>
   <Dado>
    <Ano>1991</Ano>
    <Valor>7.546</Valor>
   </Dado>
   <Dado>
    <Ano>2000</Ano>
    <Valor>8.795</Valor>
   </Dado>
   <Dado>
    <Ano>2010</Ano>
    <Valor>11.245</Valor>
   </Dado>
  </Indicador>
 </Municipio>
 <Municipio>
  <Nome>Ibateguara</Nome>
  <ID>270300</ID>
  <UF>AL</UF>
  <Indicador>
   <Nome>Moradpartperurb</Nome>
   <Dado>
    <Ano>1991</Ano>
    <Valor>7.348</Valor>
   </Dado>
   <Dado>
    <Ano>2000</Ano>
    <Valor>8.409</Valor>
   </Dado>
   <Dado>
    <Ano>2010</Ano>
    <Valor>9.333</Valor>
   </Dado>
  </Indicador>
 </Municipio>
 <Municipio>
  <Nome>Igaci</Nome>
  <ID>270310</ID>
  <UF>AL</UF>
  <Indicador>
   <Nome>Moradpartperurb</Nome>
   <Dado>
    <Ano>1991</Ano>
    <Valor>4.884</Valor>
   </Dado>
   <Dado>
    <Ano>2000</Ano>
    <Valor>5.843</Valor>
   </Dado>
   <Dado>
    <Ano>2010</Ano>
    <Valor>6.177</Valor>
   </Dado>
  </Indicador>
 </Municipio>
 <Municipio>
  <Nome>Igreja_Nova</Nome>
  <ID>270320</ID>
  <UF>AL</UF>
  <Indicador>
   <Nome>Moradpartperurb</Nome>
   <Dado>
    <Ano>1991</Ano>
    <Valor>3.987</Valor>
   </Dado>
   <Dado>
    <Ano>2000</Ano>
    <Valor>4.386</Valor>
   </Dado>
   <Dado>
    <Ano>2010</Ano>
    <Valor>4.761</Valor>
   </Dado>
  </Indicador>
 </Municipio>
 <Municipio>
  <Nome>Inhapi</Nome>
  <ID>270330</ID>
  <UF>AL</UF>
  <Indicador>
   <Nome>Moradpartperurb</Nome>
   <Dado>
    <Ano>1991</Ano>
    <Valor>4.043</Valor>
   </Dado>
   <Dado>
    <Ano>2000</Ano>
    <Valor>5.787</Valor>
   </Dado>
   <Dado>
    <Ano>2010</Ano>
    <Valor>6.677</Valor>
   </Dado>
  </Indicador>
 </Municipio>
 <Municipio>
  <Nome>Jacare_dos_Homens</Nome>
  <ID>270340</ID>
  <UF>AL</UF>
  <Indicador>
   <Nome>Moradpartperurb</Nome>
   <Dado>
    <Ano>1991</Ano>
    <Valor>2.209</Valor>
   </Dado>
   <Dado>
    <Ano>2000</Ano>
    <Valor>2.656</Valor>
   </Dado>
   <Dado>
    <Ano>2010</Ano>
    <Valor>2.979</Valor>
   </Dado>
  </Indicador>
 </Municipio>
 <Municipio>
  <Nome>Jacuipe</Nome>
  <ID>270350</ID>
  <UF>AL</UF>
  <Indicador>
   <Nome>Moradpartperurb</Nome>
   <Dado>
    <Ano>1991</Ano>
    <Valor>2.298</Valor>
   </Dado>
   <Dado>
    <Ano>2000</Ano>
    <Valor>3.344</Valor>
   </Dado>
   <Dado>
    <Ano>2010</Ano>
    <Valor>4.312</Valor>
   </Dado>
  </Indicador>
 </Municipio>
 <Municipio>
  <Nome>Japaratinga</Nome>
  <ID>270360</ID>
  <UF>AL</UF>
  <Indicador>
   <Nome>Moradpartperurb</Nome>
   <Dado>
    <Ano>1991</Ano>
    <Valor>2.224</Valor>
   </Dado>
   <Dado>
    <Ano>2000</Ano>
    <Valor>2.453</Valor>
   </Dado>
   <Dado>
    <Ano>2010</Ano>
    <Valor>3.298</Valor>
   </Dado>
  </Indicador>
 </Municipio>
 <Municipio>
  <Nome>Jaramataia</Nome>
  <ID>270370</ID>
  <UF>AL</UF>
  <Indicador>
   <Nome>Moradpartperurb</Nome>
   <Dado>
    <Ano>1991</Ano>
    <Valor>2.128</Valor>
   </Dado>
   <Dado>
    <Ano>2000</Ano>
    <Valor>2.887</Valor>
   </Dado>
   <Dado>
    <Ano>2010</Ano>
    <Valor>2.900</Valor>
   </Dado>
  </Indicador>
 </Municipio>
 <Municipio>
  <Nome>Jequia_da_Praia</Nome>
  <ID>270375</ID>
  <UF>AL</UF>
  <Indicador>
   <Nome>Moradpartperurb</Nome>
   <Dado>
    <Ano>1991</Ano>
    <Valor>0</Valor>
   </Dado>
   <Dado>
    <Ano>2000</Ano>
    <Valor>0</Valor>
   </Dado>
   <Dado>
    <Ano>2010</Ano>
    <Valor>2.790</Valor>
   </Dado>
  </Indicador>
 </Municipio>
 <Municipio>
  <Nome>Joaquim_Gomes</Nome>
  <ID>270380</ID>
  <UF>AL</UF>
  <Indicador>
   <Nome>Moradpartperurb</Nome>
   <Dado>
    <Ano>1991</Ano>
    <Valor>8.540</Valor>
   </Dado>
   <Dado>
    <Ano>2000</Ano>
    <Valor>12.564</Valor>
   </Dado>
   <Dado>
    <Ano>2010</Ano>
    <Valor>14.302</Valor>
   </Dado>
  </Indicador>
 </Municipio>
 <Municipio>
  <Nome>Jundia</Nome>
  <ID>270390</ID>
  <UF>AL</UF>
  <Indicador>
   <Nome>Moradpartperurb</Nome>
   <Dado>
    <Ano>1991</Ano>
    <Valor>1.402</Valor>
   </Dado>
   <Dado>
    <Ano>2000</Ano>
    <Valor>2.148</Valor>
   </Dado>
   <Dado>
    <Ano>2010</Ano>
    <Valor>2.798</Valor>
   </Dado>
  </Indicador>
 </Municipio>
 <Municipio>
  <Nome>Junqueiro</Nome>
  <ID>270400</ID>
  <UF>AL</UF>
  <Indicador>
   <Nome>Moradpartperurb</Nome>
   <Dado>
    <Ano>1991</Ano>
    <Valor>5.086</Valor>
   </Dado>
   <Dado>
    <Ano>2000</Ano>
    <Valor>6.957</Valor>
   </Dado>
   <Dado>
    <Ano>2010</Ano>
    <Valor>7.791</Valor>
   </Dado>
  </Indicador>
 </Municipio>
 <Municipio>
  <Nome>Lagoa_da_Canoa</Nome>
  <ID>270410</ID>
  <UF>AL</UF>
  <Indicador>
   <Nome>Moradpartperurb</Nome>
   <Dado>
    <Ano>1991</Ano>
    <Valor>4.902</Valor>
   </Dado>
   <Dado>
    <Ano>2000</Ano>
    <Valor>8.886</Valor>
   </Dado>
   <Dado>
    <Ano>2010</Ano>
    <Valor>9.147</Valor>
   </Dado>
  </Indicador>
 </Municipio>
 <Municipio>
  <Nome>Limoeiro_de_Anadia</Nome>
  <ID>270420</ID>
  <UF>AL</UF>
  <Indicador>
   <Nome>Moradpartperurb</Nome>
   <Dado>
    <Ano>1991</Ano>
    <Valor>1.528</Valor>
   </Dado>
   <Dado>
    <Ano>2000</Ano>
    <Valor>2.105</Valor>
   </Dado>
   <Dado>
    <Ano>2010</Ano>
    <Valor>2.222</Valor>
   </Dado>
  </Indicador>
 </Municipio>
 <Municipio>
  <Nome>Maceio</Nome>
  <ID>270430</ID>
  <UF>AL</UF>
  <Indicador>
   <Nome>Moradpartperurb</Nome>
   <Dado>
    <Ano>1991</Ano>
    <Valor>577.067</Valor>
   </Dado>
   <Dado>
    <Ano>2000</Ano>
    <Valor>784.388</Valor>
   </Dado>
   <Dado>
    <Ano>2010</Ano>
    <Valor>928.524</Valor>
   </Dado>
  </Indicador>
 </Municipio>
 <Municipio>
  <Nome>Major_Isidoro</Nome>
  <ID>270440</ID>
  <UF>AL</UF>
  <Indicador>
   <Nome>Moradpartperurb</Nome>
   <Dado>
    <Ano>1991</Ano>
    <Valor>7.813</Valor>
   </Dado>
   <Dado>
    <Ano>2000</Ano>
    <Valor>8.443</Valor>
   </Dado>
   <Dado>
    <Ano>2010</Ano>
    <Valor>9.288</Valor>
   </Dado>
  </Indicador>
 </Municipio>
 <Municipio>
  <Nome>Mar_Vermelho</Nome>
  <ID>270490</ID>
  <UF>AL</UF>
  <Indicador>
   <Nome>Moradpartperurb</Nome>
   <Dado>
    <Ano>1991</Ano>
    <Valor>972</Valor>
   </Dado>
   <Dado>
    <Ano>2000</Ano>
    <Valor>1.355</Valor>
   </Dado>
   <Dado>
    <Ano>2010</Ano>
    <Valor>1.632</Valor>
   </Dado>
  </Indicador>
 </Municipio>
 <Municipio>
  <Nome>Maragogi</Nome>
  <ID>270450</ID>
  <UF>AL</UF>
  <Indicador>
   <Nome>Moradpartperurb</Nome>
   <Dado>
    <Ano>1991</Ano>
    <Valor>8.871</Valor>
   </Dado>
   <Dado>
    <Ano>2000</Ano>
    <Valor>12.000</Valor>
   </Dado>
   <Dado>
    <Ano>2010</Ano>
    <Valor>18.591</Valor>
   </Dado>
  </Indicador>
 </Municipio>
 <Municipio>
  <Nome>Maravilha</Nome>
  <ID>270460</ID>
  <UF>AL</UF>
  <Indicador>
   <Nome>Moradpartperurb</Nome>
   <Dado>
    <Ano>1991</Ano>
    <Valor>3.591</Valor>
   </Dado>
   <Dado>
    <Ano>2000</Ano>
    <Valor>5.204</Valor>
   </Dado>
   <Dado>
    <Ano>2010</Ano>
    <Valor>5.117</Valor>
   </Dado>
  </Indicador>
 </Municipio>
 <Municipio>
  <Nome>Marechal_Deodoro</Nome>
  <ID>270470</ID>
  <UF>AL</UF>
  <Indicador>
   <Nome>Moradpartperurb</Nome>
   <Dado>
    <Ano>1991</Ano>
    <Valor>14.576</Valor>
   </Dado>
   <Dado>
    <Ano>2000</Ano>
    <Valor>29.314</Valor>
   </Dado>
   <Dado>
    <Ano>2010</Ano>
    <Valor>43.004</Valor>
   </Dado>
  </Indicador>
 </Municipio>
 <Municipio>
  <Nome>Maribondo</Nome>
  <ID>270480</ID>
  <UF>AL</UF>
  <Indicador>
   <Nome>Moradpartperurb</Nome>
   <Dado>
    <Ano>1991</Ano>
    <Valor>9.600</Valor>
   </Dado>
   <Dado>
    <Ano>2000</Ano>
    <Valor>10.075</Valor>
   </Dado>
   <Dado>
    <Ano>2010</Ano>
    <Valor>9.949</Valor>
   </Dado>
  </Indicador>
 </Municipio>
 <Municipio>
  <Nome>Mata_Grande</Nome>
  <ID>270500</ID>
  <UF>AL</UF>
  <Indicador>
   <Nome>Moradpartperurb</Nome>
   <Dado>
    <Ano>1991</Ano>
    <Valor>4.409</Valor>
   </Dado>
   <Dado>
    <Ano>2000</Ano>
    <Valor>4.680</Valor>
   </Dado>
   <Dado>
    <Ano>2010</Ano>
    <Valor>5.646</Valor>
   </Dado>
  </Indicador>
 </Municipio>
 <Municipio>
  <Nome>Matriz_de_Camaragibe</Nome>
  <ID>270510</ID>
  <UF>AL</UF>
  <Indicador>
   <Nome>Moradpartperurb</Nome>
   <Dado>
    <Ano>1991</Ano>
    <Valor>14.287</Valor>
   </Dado>
   <Dado>
    <Ano>2000</Ano>
    <Valor>18.179</Valor>
   </Dado>
   <Dado>
    <Ano>2010</Ano>
    <Valor>22.060</Valor>
   </Dado>
  </Indicador>
 </Municipio>
 <Municipio>
  <Nome>Messias</Nome>
  <ID>270520</ID>
  <UF>AL</UF>
  <Indicador>
   <Nome>Moradpartperurb</Nome>
   <Dado>
    <Ano>1991</Ano>
    <Valor>6.308</Valor>
   </Dado>
   <Dado>
    <Ano>2000</Ano>
    <Valor>9.429</Valor>
   </Dado>
   <Dado>
    <Ano>2010</Ano>
    <Valor>14.010</Valor>
   </Dado>
  </Indicador>
 </Municipio>
 <Municipio>
  <Nome>Minador_do_Negrao</Nome>
  <ID>270530</ID>
  <UF>AL</UF>
  <Indicador>
   <Nome>Moradpartperurb</Nome>
   <Dado>
    <Ano>1991</Ano>
    <Valor>1.607</Valor>
   </Dado>
   <Dado>
    <Ano>2000</Ano>
    <Valor>1.874</Valor>
   </Dado>
   <Dado>
    <Ano>2010</Ano>
    <Valor>2.252</Valor>
   </Dado>
  </Indicador>
 </Municipio>
 <Municipio>
  <Nome>Monteiropolis</Nome>
  <ID>270540</ID>
  <UF>AL</UF>
  <Indicador>
   <Nome>Moradpartperurb</Nome>
   <Dado>
    <Ano>1991</Ano>
    <Valor>1.801</Valor>
   </Dado>
   <Dado>
    <Ano>2000</Ano>
    <Valor>2.691</Valor>
   </Dado>
   <Dado>
    <Ano>2010</Ano>
    <Valor>2.515</Valor>
   </Dado>
  </Indicador>
 </Municipio>
 <Municipio>
  <Nome>Murici</Nome>
  <ID>270550</ID>
  <UF>AL</UF>
  <Indicador>
   <Nome>Moradpartperurb</Nome>
   <Dado>
    <Ano>1991</Ano>
    <Valor>13.573</Valor>
   </Dado>
   <Dado>
    <Ano>2000</Ano>
    <Valor>17.359</Valor>
   </Dado>
   <Dado>
    <Ano>2010</Ano>
    <Valor>20.600</Valor>
   </Dado>
  </Indicador>
 </Municipio>
 <Municipio>
  <Nome>Novo_Lino</Nome>
  <ID>270560</ID>
  <UF>AL</UF>
  <Indicador>
   <Nome>Moradpartperurb</Nome>
   <Dado>
    <Ano>1991</Ano>
    <Valor>5.127</Valor>
   </Dado>
   <Dado>
    <Ano>2000</Ano>
    <Valor>5.317</Valor>
   </Dado>
   <Dado>
    <Ano>2010</Ano>
    <Valor>7.313</Valor>
   </Dado>
  </Indicador>
 </Municipio>
 <Municipio>
  <Nome>Olho_dAgua_Grande</Nome>
  <ID>270590</ID>
  <UF>AL</UF>
  <Indicador>
   <Nome>Moradpartperurb</Nome>
   <Dado>
    <Ano>1991</Ano>
    <Valor>914</Valor>
   </Dado>
   <Dado>
    <Ano>2000</Ano>
    <Valor>1.075</Valor>
   </Dado>
   <Dado>
    <Ano>2010</Ano>
    <Valor>1.200</Valor>
   </Dado>
  </Indicador>
 </Municipio>
 <Municipio>
  <Nome>Olho_dAgua_das_Flores</Nome>
  <ID>270570</ID>
  <UF>AL</UF>
  <Indicador>
   <Nome>Moradpartperurb</Nome>
   <Dado>
    <Ano>1991</Ano>
    <Valor>9.412</Valor>
   </Dado>
   <Dado>
    <Ano>2000</Ano>
    <Valor>12.985</Valor>
   </Dado>
   <Dado>
    <Ano>2010</Ano>
    <Valor>13.912</Valor>
   </Dado>
  </Indicador>
 </Municipio>
 <Municipio>
  <Nome>Olho_dAgua_do_Casado</Nome>
  <ID>270580</ID>
  <UF>AL</UF>
  <Indicador>
   <Nome>Moradpartperurb</Nome>
   <Dado>
    <Ano>1991</Ano>
    <Valor>3.704</Valor>
   </Dado>
   <Dado>
    <Ano>2000</Ano>
    <Valor>3.883</Valor>
   </Dado>
   <Dado>
    <Ano>2010</Ano>
    <Valor>4.002</Valor>
   </Dado>
  </Indicador>
 </Municipio>
 <Municipio>
  <Nome>Olivenca</Nome>
  <ID>270600</ID>
  <UF>AL</UF>
  <Indicador>
   <Nome>Moradpartperurb</Nome>
   <Dado>
    <Ano>1991</Ano>
    <Valor>1.599</Valor>
   </Dado>
   <Dado>
    <Ano>2000</Ano>
    <Valor>2.371</Valor>
   </Dado>
   <Dado>
    <Ano>2010</Ano>
    <Valor>3.115</Valor>
   </Dado>
  </Indicador>
 </Municipio>
 <Municipio>
  <Nome>Ouro_Branco</Nome>
  <ID>270610</ID>
  <UF>AL</UF>
  <Indicador>
   <Nome>Moradpartperurb</Nome>
   <Dado>
    <Ano>1991</Ano>
    <Valor>4.377</Valor>
   </Dado>
   <Dado>
    <Ano>2000</Ano>
    <Valor>5.258</Valor>
   </Dado>
   <Dado>
    <Ano>2010</Ano>
    <Valor>6.846</Valor>
   </Dado>
  </Indicador>
 </Municipio>
 <Municipio>
  <Nome>Palestina</Nome>
  <ID>270620</ID>
  <UF>AL</UF>
  <Indicador>
   <Nome>Moradpartperurb</Nome>
   <Dado>
    <Ano>1991</Ano>
    <Valor>2.200</Valor>
   </Dado>
   <Dado>
    <Ano>2000</Ano>
    <Valor>2.975</Valor>
   </Dado>
   <Dado>
    <Ano>2010</Ano>
    <Valor>3.224</Valor>
   </Dado>
  </Indicador>
 </Municipio>
 <Municipio>
  <Nome>Palmeira_dos_Indios</Nome>
  <ID>270630</ID>
  <UF>AL</UF>
  <Indicador>
   <Nome>Moradpartperurb</Nome>
   <Dado>
    <Ano>1991</Ano>
    <Valor>46.187</Valor>
   </Dado>
   <Dado>
    <Ano>2000</Ano>
    <Valor>48.708</Valor>
   </Dado>
   <Dado>
    <Ano>2010</Ano>
    <Valor>51.439</Valor>
   </Dado>
  </Indicador>
 </Municipio>
 <Municipio>
  <Nome>Pao_de_Acucar</Nome>
  <ID>270640</ID>
  <UF>AL</UF>
  <Indicador>
   <Nome>Moradpartperurb</Nome>
   <Dado>
    <Ano>1991</Ano>
    <Valor>8.962</Valor>
   </Dado>
   <Dado>
    <Ano>2000</Ano>
    <Valor>10.778</Valor>
   </Dado>
   <Dado>
    <Ano>2010</Ano>
    <Valor>10.750</Valor>
   </Dado>
  </Indicador>
 </Municipio>
 <Municipio>
  <Nome>Pariconha</Nome>
  <ID>270642</ID>
  <UF>AL</UF>
  <Indicador>
   <Nome>Moradpartperurb</Nome>
   <Dado>
    <Ano>1991</Ano>
    <Valor>0</Valor>
   </Dado>
   <Dado>
    <Ano>2000</Ano>
    <Valor>2.404</Valor>
   </Dado>
   <Dado>
    <Ano>2010</Ano>
    <Valor>2.794</Valor>
   </Dado>
  </Indicador>
 </Municipio>
 <Municipio>
  <Nome>Paripueira</Nome>
  <ID>270644</ID>
  <UF>AL</UF>
  <Indicador>
   <Nome>Moradpartperurb</Nome>
   <Dado>
    <Ano>1991</Ano>
    <Valor>0</Valor>
   </Dado>
   <Dado>
    <Ano>2000</Ano>
    <Valor>7.043</Valor>
   </Dado>
   <Dado>
    <Ano>2010</Ano>
    <Valor>10.002</Valor>
   </Dado>
  </Indicador>
 </Municipio>
 <Municipio>
  <Nome>Passo_de_Camaragibe</Nome>
  <ID>270650</ID>
  <UF>AL</UF>
  <Indicador>
   <Nome>Moradpartperurb</Nome>
   <Dado>
    <Ano>1991</Ano>
    <Valor>5.315</Valor>
   </Dado>
   <Dado>
    <Ano>2000</Ano>
    <Valor>5.705</Valor>
   </Dado>
   <Dado>
    <Ano>2010</Ano>
    <Valor>7.219</Valor>
   </Dado>
  </Indicador>
 </Municipio>
 <Municipio>
  <Nome>Paulo_Jacinto</Nome>
  <ID>270660</ID>
  <UF>AL</UF>
  <Indicador>
   <Nome>Moradpartperurb</Nome>
   <Dado>
    <Ano>1991</Ano>
    <Valor>4.453</Valor>
   </Dado>
   <Dado>
    <Ano>2000</Ano>
    <Valor>4.661</Valor>
   </Dado>
   <Dado>
    <Ano>2010</Ano>
    <Valor>4.896</Valor>
   </Dado>
  </Indicador>
 </Municipio>
 <Municipio>
  <Nome>Penedo</Nome>
  <ID>270670</ID>
  <UF>AL</UF>
  <Indicador>
   <Nome>Moradpartperurb</Nome>
   <Dado>
    <Ano>1991</Ano>
    <Valor>38.329</Valor>
   </Dado>
   <Dado>
    <Ano>2000</Ano>
    <Valor>41.350</Valor>
   </Dado>
   <Dado>
    <Ano>2010</Ano>
    <Valor>44.896</Valor>
   </Dado>
  </Indicador>
 </Municipio>
 <Municipio>
  <Nome>Piacabucu</Nome>
  <ID>270680</ID>
  <UF>AL</UF>
  <Indicador>
   <Nome>Moradpartperurb</Nome>
   <Dado>
    <Ano>1991</Ano>
    <Valor>10.159</Valor>
   </Dado>
   <Dado>
    <Ano>2000</Ano>
    <Valor>10.112</Valor>
   </Dado>
   <Dado>
    <Ano>2010</Ano>
    <Valor>10.419</Valor>
   </Dado>
  </Indicador>
 </Municipio>
 <Municipio>
  <Nome>Pilar</Nome>
  <ID>270690</ID>
  <UF>AL</UF>
  <Indicador>
   <Nome>Moradpartperurb</Nome>
   <Dado>
    <Ano>1991</Ano>
    <Valor>22.188</Valor>
   </Dado>
   <Dado>
    <Ano>2000</Ano>
    <Valor>28.086</Valor>
   </Dado>
   <Dado>
    <Ano>2010</Ano>
    <Valor>31.759</Valor>
   </Dado>
  </Indicador>
 </Municipio>
 <Municipio>
  <Nome>Pindoba</Nome>
  <ID>270700</ID>
  <UF>AL</UF>
  <Indicador>
   <Nome>Moradpartperurb</Nome>
   <Dado>
    <Ano>1991</Ano>
    <Valor>1.232</Valor>
   </Dado>
   <Dado>
    <Ano>2000</Ano>
    <Valor>1.304</Valor>
   </Dado>
   <Dado>
    <Ano>2010</Ano>
    <Valor>1.619</Valor>
   </Dado>
  </Indicador>
 </Municipio>
 <Municipio>
  <Nome>Piranhas</Nome>
  <ID>270710</ID>
  <UF>AL</UF>
  <Indicador>
   <Nome>Moradpartperurb</Nome>
   <Dado>
    <Ano>1991</Ano>
    <Valor>1.697</Valor>
   </Dado>
   <Dado>
    <Ano>2000</Ano>
    <Valor>1.328</Valor>
   </Dado>
   <Dado>
    <Ano>2010</Ano>
    <Valor>13.138</Valor>
   </Dado>
  </Indicador>
 </Municipio>
 <Municipio>
  <Nome>Poco_das_Trincheiras</Nome>
  <ID>270720</ID>
  <UF>AL</UF>
  <Indicador>
   <Nome>Moradpartperurb</Nome>
   <Dado>
    <Ano>1991</Ano>
    <Valor>1.189</Valor>
   </Dado>
   <Dado>
    <Ano>2000</Ano>
    <Valor>1.515</Valor>
   </Dado>
   <Dado>
    <Ano>2010</Ano>
    <Valor>2.000</Valor>
   </Dado>
  </Indicador>
 </Municipio>
 <Municipio>
  <Nome>Porto_Calvo</Nome>
  <ID>270730</ID>
  <UF>AL</UF>
  <Indicador>
   <Nome>Moradpartperurb</Nome>
   <Dado>
    <Ano>1991</Ano>
    <Valor>11.129</Valor>
   </Dado>
   <Dado>
    <Ano>2000</Ano>
    <Valor>14.777</Valor>
   </Dado>
   <Dado>
    <Ano>2010</Ano>
    <Valor>20.164</Valor>
   </Dado>
  </Indicador>
 </Municipio>
 <Municipio>
  <Nome>Porto_Real_do_Colegio</Nome>
  <ID>270750</ID>
  <UF>AL</UF>
  <Indicador>
   <Nome>Moradpartperurb</Nome>
   <Dado>
    <Ano>1991</Ano>
    <Valor>5.724</Valor>
   </Dado>
   <Dado>
    <Ano>2000</Ano>
    <Valor>5.930</Valor>
   </Dado>
   <Dado>
    <Ano>2010</Ano>
    <Valor>6.558</Valor>
   </Dado>
  </Indicador>
 </Municipio>
 <Municipio>
  <Nome>Porto_de_Pedras</Nome>
  <ID>270740</ID>
  <UF>AL</UF>
  <Indicador>
   <Nome>Moradpartperurb</Nome>
   <Dado>
    <Ano>1991</Ano>
    <Valor>4.035</Valor>
   </Dado>
   <Dado>
    <Ano>2000</Ano>
    <Valor>5.198</Valor>
   </Dado>
   <Dado>
    <Ano>2010</Ano>
    <Valor>4.793</Valor>
   </Dado>
  </Indicador>
 </Municipio>
 <Municipio>
  <Nome>Quebrangulo</Nome>
  <ID>270760</ID>
  <UF>AL</UF>
  <Indicador>
   <Nome>Moradpartperurb</Nome>
   <Dado>
    <Ano>1991</Ano>
    <Valor>5.418</Valor>
   </Dado>
   <Dado>
    <Ano>2000</Ano>
    <Valor>6.133</Valor>
   </Dado>
   <Dado>
    <Ano>2010</Ano>
    <Valor>6.419</Valor>
   </Dado>
  </Indicador>
 </Municipio>
 <Municipio>
  <Nome>Rio_Largo</Nome>
  <ID>270770</ID>
  <UF>AL</UF>
  <Indicador>
   <Nome>Moradpartperurb</Nome>
   <Dado>
    <Ano>1991</Ano>
    <Valor>38.304</Valor>
   </Dado>
   <Dado>
    <Ano>2000</Ano>
    <Valor>49.617</Valor>
   </Dado>
   <Dado>
    <Ano>2010</Ano>
    <Valor>55.126</Valor>
   </Dado>
  </Indicador>
 </Municipio>
 <Municipio>
  <Nome>Roteiro</Nome>
  <ID>270780</ID>
  <UF>AL</UF>
  <Indicador>
   <Nome>Moradpartperurb</Nome>
   <Dado>
    <Ano>1991</Ano>
    <Valor>4.010</Valor>
   </Dado>
   <Dado>
    <Ano>2000</Ano>
    <Valor>5.455</Valor>
   </Dado>
   <Dado>
    <Ano>2010</Ano>
    <Valor>5.802</Valor>
   </Dado>
  </Indicador>
 </Municipio>
 <Municipio>
  <Nome>Santa_Luzia_do_Norte</Nome>
  <ID>270790</ID>
  <UF>AL</UF>
  <Indicador>
   <Nome>Moradpartperurb</Nome>
   <Dado>
    <Ano>1991</Ano>
    <Valor>5.039</Valor>
   </Dado>
   <Dado>
    <Ano>2000</Ano>
    <Valor>5.303</Valor>
   </Dado>
   <Dado>
    <Ano>2010</Ano>
    <Valor>6.172</Valor>
   </Dado>
  </Indicador>
 </Municipio>
 <Municipio>
  <Nome>Santana_do_Ipanema</Nome>
  <ID>270800</ID>
  <UF>AL</UF>
  <Indicador>
   <Nome>Moradpartperurb</Nome>
   <Dado>
    <Ano>1991</Ano>
    <Valor>20.035</Valor>
   </Dado>
   <Dado>
    <Ano>2000</Ano>
    <Valor>23.869</Valor>
   </Dado>
   <Dado>
    <Ano>2010</Ano>
    <Valor>27.075</Valor>
   </Dado>
  </Indicador>
 </Municipio>
 <Municipio>
  <Nome>Santana_do_Mundau</Nome>
  <ID>270810</ID>
  <UF>AL</UF>
  <Indicador>
   <Nome>Moradpartperurb</Nome>
   <Dado>
    <Ano>1991</Ano>
    <Valor>5.665</Valor>
   </Dado>
   <Dado>
    <Ano>2000</Ano>
    <Valor>6.173</Valor>
   </Dado>
   <Dado>
    <Ano>2010</Ano>
    <Valor>5.509</Valor>
   </Dado>
  </Indicador>
 </Municipio>
 <Municipio>
  <Nome>Sao_Bras</Nome>
  <ID>270820</ID>
  <UF>AL</UF>
  <Indicador>
   <Nome>Moradpartperurb</Nome>
   <Dado>
    <Ano>1991</Ano>
    <Valor>2.731</Valor>
   </Dado>
   <Dado>
    <Ano>2000</Ano>
    <Valor>3.006</Valor>
   </Dado>
   <Dado>
    <Ano>2010</Ano>
    <Valor>3.171</Valor>
   </Dado>
  </Indicador>
 </Municipio>
 <Municipio>
  <Nome>Sao_Jose_da_Laje</Nome>
  <ID>270830</ID>
  <UF>AL</UF>
  <Indicador>
   <Nome>Moradpartperurb</Nome>
   <Dado>
    <Ano>1991</Ano>
    <Valor>10.844</Valor>
   </Dado>
   <Dado>
    <Ano>2000</Ano>
    <Valor>12.473</Valor>
   </Dado>
   <Dado>
    <Ano>2010</Ano>
    <Valor>15.193</Valor>
   </Dado>
  </Indicador>
 </Municipio>
 <Municipio>
  <Nome>Sao_Jose_da_Tapera</Nome>
  <ID>270840</ID>
  <UF>AL</UF>
  <Indicador>
   <Nome>Moradpartperurb</Nome>
   <Dado>
    <Ano>1991</Ano>
    <Valor>6.334</Valor>
   </Dado>
   <Dado>
    <Ano>2000</Ano>
    <Valor>9.261</Valor>
   </Dado>
   <Dado>
    <Ano>2010</Ano>
    <Valor>11.609</Valor>
   </Dado>
  </Indicador>
 </Municipio>
 <Municipio>
  <Nome>Sao_Luis_do_Quitunde</Nome>
  <ID>270850</ID>
  <UF>AL</UF>
  <Indicador>
   <Nome>Moradpartperurb</Nome>
   <Dado>
    <Ano>1991</Ano>
    <Valor>13.448</Valor>
   </Dado>
   <Dado>
    <Ano>2000</Ano>
    <Valor>17.348</Valor>
   </Dado>
   <Dado>
    <Ano>2010</Ano>
    <Valor>20.552</Valor>
   </Dado>
  </Indicador>
 </Municipio>
 <Municipio>
  <Nome>Sao_Miguel_dos_Campos</Nome>
  <ID>270860</ID>
  <UF>AL</UF>
  <Indicador>
   <Nome>Moradpartperurb</Nome>
   <Dado>
    <Ano>1991</Ano>
    <Valor>27.892</Valor>
   </Dado>
   <Dado>
    <Ano>2000</Ano>
    <Valor>35.031</Valor>
   </Dado>
   <Dado>
    <Ano>2010</Ano>
    <Valor>51.997</Valor>
   </Dado>
  </Indicador>
 </Municipio>
 <Municipio>
  <Nome>Sao_Miguel_dos_Milagres</Nome>
  <ID>270870</ID>
  <UF>AL</UF>
  <Indicador>
   <Nome>Moradpartperurb</Nome>
   <Dado>
    <Ano>1991</Ano>
    <Valor>1.130</Valor>
   </Dado>
   <Dado>
    <Ano>2000</Ano>
    <Valor>1.744</Valor>
   </Dado>
   <Dado>
    <Ano>2010</Ano>
    <Valor>2.242</Valor>
   </Dado>
  </Indicador>
 </Municipio>
 <Municipio>
  <Nome>Sao_Sebastiao</Nome>
  <ID>270880</ID>
  <UF>AL</UF>
  <Indicador>
   <Nome>Moradpartperurb</Nome>
   <Dado>
    <Ano>1991</Ano>
    <Valor>7.345</Valor>
   </Dado>
   <Dado>
    <Ano>2000</Ano>
    <Valor>9.408</Valor>
   </Dado>
   <Dado>
    <Ano>2010</Ano>
    <Valor>12.297</Valor>
   </Dado>
  </Indicador>
 </Municipio>
 <Municipio>
  <Nome>Satuba</Nome>
  <ID>270890</ID>
  <UF>AL</UF>
  <Indicador>
   <Nome>Moradpartperurb</Nome>
   <Dado>
    <Ano>1991</Ano>
    <Valor>5.736</Valor>
   </Dado>
   <Dado>
    <Ano>2000</Ano>
    <Valor>9.946</Valor>
   </Dado>
   <Dado>
    <Ano>2010</Ano>
    <Valor>12.792</Valor>
   </Dado>
  </Indicador>
 </Municipio>
 <Municipio>
  <Nome>Senador_Rui_Palmeira</Nome>
  <ID>270895</ID>
  <UF>AL</UF>
  <Indicador>
   <Nome>Moradpartperurb</Nome>
   <Dado>
    <Ano>1991</Ano>
    <Valor>3.062</Valor>
   </Dado>
   <Dado>
    <Ano>2000</Ano>
    <Valor>3.414</Valor>
   </Dado>
   <Dado>
    <Ano>2010</Ano>
    <Valor>3.892</Valor>
   </Dado>
  </Indicador>
 </Municipio>
 <Municipio>
  <Nome>Tanque_dArca</Nome>
  <ID>270900</ID>
  <UF>AL</UF>
  <Indicador>
   <Nome>Moradpartperurb</Nome>
   <Dado>
    <Ano>1991</Ano>
    <Valor>2.044</Valor>
   </Dado>
   <Dado>
    <Ano>2000</Ano>
    <Valor>2.058</Valor>
   </Dado>
   <Dado>
    <Ano>2010</Ano>
    <Valor>2.138</Valor>
   </Dado>
  </Indicador>
 </Municipio>
 <Municipio>
  <Nome>Taquarana</Nome>
  <ID>270910</ID>
  <UF>AL</UF>
  <Indicador>
   <Nome>Moradpartperurb</Nome>
   <Dado>
    <Ano>1991</Ano>
    <Valor>3.491</Valor>
   </Dado>
   <Dado>
    <Ano>2000</Ano>
    <Valor>4.336</Valor>
   </Dado>
   <Dado>
    <Ano>2010</Ano>
    <Valor>7.299</Valor>
   </Dado>
  </Indicador>
 </Municipio>
 <Municipio>
  <Nome>Teotonio_Vilela</Nome>
  <ID>270915</ID>
  <UF>AL</UF>
  <Indicador>
   <Nome>Moradpartperurb</Nome>
   <Dado>
    <Ano>1991</Ano>
    <Valor>21.779</Valor>
   </Dado>
   <Dado>
    <Ano>2000</Ano>
    <Valor>29.533</Valor>
   </Dado>
   <Dado>
    <Ano>2010</Ano>
    <Valor>34.694</Valor>
   </Dado>
  </Indicador>
 </Municipio>
 <Municipio>
  <Nome>Traipu</Nome>
  <ID>270920</ID>
  <UF>AL</UF>
  <Indicador>
   <Nome>Moradpartperurb</Nome>
   <Dado>
    <Ano>1991</Ano>
    <Valor>6.329</Valor>
   </Dado>
   <Dado>
    <Ano>2000</Ano>
    <Valor>6.766</Valor>
   </Dado>
   <Dado>
    <Ano>2010</Ano>
    <Valor>8.015</Valor>
   </Dado>
  </Indicador>
 </Municipio>
 <Municipio>
  <Nome>Uniao_dos_Palmares</Nome>
  <ID>270930</ID>
  <UF>AL</UF>
  <Indicador>
   <Nome>Moradpartperurb</Nome>
   <Dado>
    <Ano>1991</Ano>
    <Valor>33.501</Valor>
   </Dado>
   <Dado>
    <Ano>2000</Ano>
    <Valor>37.453</Valor>
   </Dado>
   <Dado>
    <Ano>2010</Ano>
    <Valor>45.873</Valor>
   </Dado>
  </Indicador>
 </Municipio>
 <Municipio>
  <Nome>Vicosa</Nome>
  <ID>270940</ID>
  <UF>AL</UF>
  <Indicador>
   <Nome>Moradpartperurb</Nome>
   <Dado>
    <Ano>1991</Ano>
    <Valor>14.010</Valor>
   </Dado>
   <Dado>
    <Ano>2000</Ano>
    <Valor>17.189</Valor>
   </Dado>
   <Dado>
    <Ano>2010</Ano>
    <Valor>18.115</Valor>
   </Dado>
  </Indicador>
 </Municipio>
 <Foot/>
</document>